sign_xpi_lib/__init__.py
sign_xpi_lib/sign_xpi_lib.py
sign_xpi_lib-0.1.0.dist-info/DESCRIPTION.rst
sign_xpi_lib-0.1.0.dist-info/METADATA
sign_xpi_lib-0.1.0.dist-info/RECORD
sign_xpi_lib-0.1.0.dist-info/WHEEL
sign_xpi_lib-0.1.0.dist-info/metadata.json
sign_xpi_lib-0.1.0.dist-info/top_level.txt
