Metadata-Version: 2.0
Name: sign-xpi-lib
Version: 0.1.0
Summary: A library to handle the manipulations of signing XPIs at Mozilla.
Home-page: https://github.com/mozilla-services/sign-xpi-lib
Author: Ethan Glasser-Camp
Author-email: eglassercamp@mozilla.com
License: MPL
Keywords: sign_xpi
Platform: UNKNOWN
Classifier: Development Status :: 2 - Pre-Alpha
Classifier: Intended Audience :: Developers
Classifier: License :: OSI Approved :: Mozilla Public License 2.0 (MPL 2.0)
Classifier: Natural Language :: English
Classifier: Programming Language :: Python :: 3
Classifier: Programming Language :: Python :: 3.3
Classifier: Programming Language :: Python :: 3.4
Classifier: Programming Language :: Python :: 3.5
Classifier: Programming Language :: Python :: 3.6
